__init__.py
kafka_wrapper/__init__.py
kafka_wrapper/apps.py
kafka_wrapper/base.py
kafka_wrapper/consumers.py
kafka_wrapper/enum.py
kafka_wrapper/producers.py
kafka_wrapper/settings.py
kafka_wrapper/management/__init__.py
kafka_wrapper/management/commands/__init__.py
kafka_wrapper/management/commands/run_kafka_consumers.py
django_kafka_wrapper-0.1.7.dist-info/LICENSE
django_kafka_wrapper-0.1.7.dist-info/METADATA
django_kafka_wrapper-0.1.7.dist-info/WHEEL
django_kafka_wrapper-0.1.7.dist-info/top_level.txt
django_kafka_wrapper-0.1.7.dist-info/RECORD
